peakrdl_systemrdl/__about__.py
peakrdl_systemrdl/__init__.py
peakrdl_systemrdl/__peakrdl__.py
peakrdl_systemrdl/definition_generator.py
peakrdl_systemrdl/exporter.py
peakrdl_systemrdl/identifier_filter.py
peakrdl_systemrdl/rdl_generator.py
peakrdl_systemrdl/stringify.py
peakrdl_systemrdl-1.0.1.dist-info/licenses/LICENSE
peakrdl_systemrdl-1.0.1.dist-info/METADATA
peakrdl_systemrdl-1.0.1.dist-info/WHEEL
peakrdl_systemrdl-1.0.1.dist-info/entry_points.txt
peakrdl_systemrdl-1.0.1.dist-info/top_level.txt
peakrdl_systemrdl-1.0.1.dist-info/RECORD
