Metadata-Version: 2.4
Name: peakrdl-systemrdl
Version: 1.0.1
Summary: Write a register model to a SystemRDL file
Author: Alex Mykyta
License: LGPLv3
Project-URL: Source, https://github.com/SystemRDL/PeakRDL-systemrdl
Project-URL: Tracker, https://github.com/SystemRDL/PeakRDL-systemrdl/issues
Project-URL: Changelog, https://github.com/SystemRDL/PeakRDL-systemrdl/releases
Keywords: SystemRDL,PeakRDL,CSR,compiler,tool,registers,generator
Classifier: Development Status :: 5 - Production/Stable
Classifier: Programming Language :: Python
Classifier: Programming Language :: Python :: 3
Classifier: Programming Language :: Python :: 3 :: Only
Classifier: Intended Audience :: Developers
Classifier: License :: OSI Approved :: GNU Lesser General Public License v3 (LGPLv3)
Classifier: Operating System :: OS Independent
Classifier: Topic :: Scientific/Engineering :: Electronic Design Automation (EDA)
Requires-Python: >=3.7
License-File: LICENSE
Requires-Dist: systemrdl-compiler~=1.30
Provides-Extra: cli
Requires-Dist: peakrdl-cli>=1.5.0; extra == "cli"
Dynamic: license-file
